hogpp/__init__.py
hogpp/_hogpp.cpython-314-x86_64-linux-musl.so
hogpp.libs/libgcc_s-0cd532bd.so.1
hogpp.libs/libstdc++-5d72f927.so.6.0.33
hogpp-0.2.1.dist-info/METADATA
hogpp-0.2.1.dist-info/WHEEL
hogpp-0.2.1.dist-info/RECORD
hogpp-0.2.1.dist-info/licenses/LICENSE
hogpp-0.2.1.dist-info/sboms/auditwheel.cdx.json
