Metadata-Version: 2.1
Name: hogpp
Version: 0.2.1
Summary: Fast computation of rectangular histogram of oriented gradients (R-HOG) features using integral histogram
Author-Email: Sergiu Deitsch <sergiu.deitsch@gmail.com>
License: Apache License (2.0)
Classifier: Development Status :: 3 - Alpha
Classifier: Intended Audience :: Developers
Classifier: Intended Audience :: End Users/Desktop
Classifier: Intended Audience :: Science/Research
Classifier: License :: OSI Approved :: Apache Software License
Classifier: Operating System :: OS Independent
Classifier: Programming Language :: Python :: 3
Classifier: Programming Language :: Python :: 3.9
Classifier: Programming Language :: Python :: 3.10
Classifier: Programming Language :: Python :: 3.11
Classifier: Programming Language :: Python :: 3.12
Classifier: Programming Language :: Python :: 3.13
Classifier: Programming Language :: Python :: 3.14
Classifier: Programming Language :: Python :: Implementation :: CPython
Classifier: Programming Language :: Python :: Implementation :: PyPy
Classifier: Topic :: Scientific/Engineering :: Information Analysis
Classifier: Topic :: Software Development :: Libraries :: Python Modules
Project-URL: Documentation, https://hogpp.readthedocs.io
Project-URL: Issues, https://github.com/sergiud/hogpp/issues
Project-URL: Source, https://github.com/sergiud/hogpp
Requires-Python: >=3.9
Requires-Dist: numpy
